api_client/__init__.py
api_client/tessell_api_client.py
mcp_core/__init__.py
mcp_core/app_config.py
mcp_core/auth_config.py
mcp_core/context.py
mcp_core/mcp_server.py
mcp_core/tools/__init__.py
mcp_core/tools/client_factory.py
mcp_core/tools/docs.py
mcp_core/tools/database/__init__.py
mcp_core/tools/database/database.py
mcp_core/tools/database/base/__init__.py
mcp_core/tools/database/base/connection_manager.py
mcp_core/tools/database/base/database_engine.py
mcp_core/tools/database/base/query_validator.py
mcp_core/tools/database/oracle/oracle_engine.py
mcp_core/tools/database/oracle/oracle_queries.py
mcp_core/tools/database/postgresql/__init__.py
mcp_core/tools/database/postgresql/postgresql_engine.py
mcp_core/tools/database/postgresql/postgresql_queries.py
mcp_core/tools/service/__init__.py
mcp_core/tools/service/availability_machine.py
mcp_core/tools/service/services.py
tessell_mcp/__init__.py
tessell_mcp/main.py
tessell_mcp-0.1.14.dist-info/METADATA
tessell_mcp-0.1.14.dist-info/WHEEL
tessell_mcp-0.1.14.dist-info/entry_points.txt
tessell_mcp-0.1.14.dist-info/top_level.txt
tessell_mcp-0.1.14.dist-info/RECORD
