Metadata-Version: 2.4
Name: tessell-mcp
Version: 0.1.14
Summary: Tessell Model Context Protocol (MCP) server
Author-email: Tessell <contact@tessell.com>
Requires-Python: >=3.13
Requires-Dist: httpx<1.0.0,>=0.28.1
Requires-Dist: mcp<2.0.0,>=1.11.0
Requires-Dist: oracledb>=3.2.0
Requires-Dist: psycopg2>=2.9.10
Requires-Dist: python-dotenv<2.0.0,>=1.1.1
Requires-Dist: requests>=2.32.4
